izzy_heartbeat/__init__.py
izzy_heartbeat/heartbeat.py
izzy_heartbeat/logger.py
izzy_heartbeat/message_type.py
izzy_heartbeat/ports.py
izzy_heartbeat-0.2.4.dist-info/METADATA
izzy_heartbeat-0.2.4.dist-info/WHEEL
izzy_heartbeat-0.2.4.dist-info/RECORD
