Metadata-Version: 2.4
Name: izzy-heartbeat
Version: 0.2.4
Summary: Heartbeat classes for the IZZY Project.
Project-URL: repository, https://github.com/rmdPurdue/izzy-heartbeat
Author-email: Rich Dionne <rdionne@purdue.edu>
Classifier: Development Status :: 3 - Alpha
Classifier: License :: OSI Approved :: GNU General Public License v3 (GPLv3)
Classifier: Programming Language :: Python
Requires-Python: >=3.13
